pslipstream/__init__.py
pslipstream/__main__.py
pslipstream/config.py
pslipstream/device.py
pslipstream/dvd.py
pslipstream/exceptions.py
pslipstream/gui/__init__.py
pslipstream/gui/main_window.py
pslipstream/gui/main_window.ui
pslipstream/gui/main_window_ui.py
pslipstream/gui/workers.py
pslipstream/helpers.py
pslipstream/main.py
pslipstream/static/img/icon.ico
pslipstream/static/img/icon.xcf
pslipstream/static/img/info-circle.svg
pslipstream/static/img/music-disc-with-luster.svg
pslipstream/static/img/refresh.svg
pslipstream/static/README.md
pslipstream/static/style.qss
pslipstream-1.0.0.dist-info/entry_points.txt
pslipstream-1.0.0.dist-info/LICENSE
pslipstream-1.0.0.dist-info/METADATA
pslipstream-1.0.0.dist-info/WHEEL
pslipstream-1.0.0.dist-info/RECORD
