Metadata-Version: 2.1
Name: pslipstream
Version: 1.0.0
Summary: The most informative Home-media backup solution.
Home-page: https://github.com/rlaphoenix/slipstream
License: GPLv3
Keywords: python,dvd,backup
Author: rlaphoenix
Author-email: rlaphoenix@pm.me
Requires-Python: >=3.8,<3.12
Classifier: Development Status :: 4 - Beta
Classifier: Intended Audience :: End Users/Desktop
Classifier: License :: Other/Proprietary License
Classifier: Natural Language :: English
Classifier: Operating System :: Microsoft :: Windows
Classifier: Operating System :: Microsoft :: Windows :: Windows 10
Classifier: Operating System :: Microsoft :: Windows :: Windows 11
Classifier: Operating System :: Microsoft :: Windows :: Windows 7
Classifier: Operating System :: Microsoft :: Windows :: Windows 8
Classifier: Operating System :: Microsoft :: Windows :: Windows 8.1
Classifier: Operating System :: Microsoft :: Windows :: Windows Server 2008
Classifier: Programming Language :: Python :: 3
Classifier: Programming Language :: Python :: 3.8
Classifier: Programming Language :: Python :: 3.9
Classifier: Programming Language :: Python :: 3.10
Classifier: Programming Language :: Python :: 3.11
Classifier: Topic :: Multimedia
Classifier: Topic :: Multimedia :: Video
Classifier: Topic :: Multimedia :: Video :: Conversion
Classifier: Topic :: Security :: Cryptography
Provides-Extra: pyinstaller
Requires-Dist: PySide6-Essentials (>=6.5.3,<7.0.0)
Requires-Dist: WMI (>=1.5.1,<2.0.0) ; sys_platform == "win32"
Requires-Dist: appdirs (>=1.4.4,<2.0.0)
Requires-Dist: click (>=8.1.7,<9.0.0)
Requires-Dist: coloredlogs (>=15.0.1,<16.0.0)
Requires-Dist: jsonpickle (>=3.0.2,<4.0.0)
Requires-Dist: pycdlib (>=1.14.0,<2.0.0)
Requires-Dist: pydvdcss (>=1.4.0,<2.0.0)
Requires-Dist: pydvdid-m (>=1.1.1,<2.0.0)
Requires-Dist: pyinstaller (>=6.0.0,<7.0.0) ; extra == "pyinstaller"
Requires-Dist: pywin32 (==306) ; sys_platform == "win32"
Requires-Dist: tqdm (>=4.66.1,<5.0.0)
Project-URL: Bug Tracker, https://github.com/rlaphoenix/slipstream/issues
Project-URL: Changelog, https://github.com/rlaphoenix/slipstream/blob/master/CHANGELOG.md
Project-URL: Forums, https://github.com/rlaphoenix/slipstream/discussions
Project-URL: Repository, https://github.com/rlaphoenix/slipstream
